Topsis_shruti/topsis.py
Topsis_shruti-1.0.0.dist-info/METADATA
Topsis_shruti-1.0.0.dist-info/RECORD
Topsis_shruti-1.0.0.dist-info/WHEEL
Topsis_shruti-1.0.0.dist-info/entry_points.txt
Topsis_shruti-1.0.0.dist-info/top_level.txt
