Metadata-Version: 2.1
Name: Topsis-shruti
Version: 1.0.0
Summary: A Python package to get the the topsis score and rank
Home-page: UNKNOWN
Author: Shruti Agrawal
License: MIT
Platform: UNKNOWN
Classifier: License :: OSI Approved :: MIT License
Classifier: Programming Language :: Python :: 3
Classifier: Programming Language :: Python :: 3.7
Requires-Dist: requests
Requires-Dist: pandas
Requires-Dist: numpy
